setup.py
Flask_ReqArg.egg-info/PKG-INFO
Flask_ReqArg.egg-info/SOURCES.txt
Flask_ReqArg.egg-info/dependency_links.txt
Flask_ReqArg.egg-info/not-zip-safe
Flask_ReqArg.egg-info/requires.txt
Flask_ReqArg.egg-info/top_level.txt
flask_reqarg/__init__.py
flask_reqarg/base.py