Metadata-Version: 1.1
Name: Flask-ReqArg
Version: 0.1.4
Summary: The decorator that maps request arguments into function arguments.
Home-page: https://github.com/jason2506/flask-reqarg/
Author: Chi-En Wu
Author-email: UNKNOWN
License: BSD
Platform: any
Classifier: Environment :: Web Environment
Classifier: Intended Audience :: Developers
Classifier: License :: OSI Approved :: BSD License
Classifier: Operating System :: OS Independent
Classifier: Programming Language :: Python
Classifier: Topic :: Internet :: WWW/HTTP :: Dynamic Content
Classifier: Topic :: Software Development :: Libraries :: Python Modules
